mongopatcher/__init__.py
mongopatcher/mongopatcher.py
mongopatcher/tools.py
mongopatcher/extensions/__init__.py
mongopatcher/extensions/flask.py
mongopatcher-0.3.2.dist-info/DESCRIPTION.rst
mongopatcher-0.3.2.dist-info/METADATA
mongopatcher-0.3.2.dist-info/RECORD
mongopatcher-0.3.2.dist-info/WHEEL
mongopatcher-0.3.2.dist-info/metadata.json
mongopatcher-0.3.2.dist-info/top_level.txt
